jenkins_jobs_fail_the_build/__init__.py
jenkins_jobs_fail_the_build/builders.py
jenkins_jobs_fail_the_build-1.0.dist-info/top_level.txt
jenkins_jobs_fail_the_build-1.0.dist-info/entry_points.txt
jenkins_jobs_fail_the_build-1.0.dist-info/METADATA
jenkins_jobs_fail_the_build-1.0.dist-info/DESCRIPTION.rst
jenkins_jobs_fail_the_build-1.0.dist-info/metadata.json
jenkins_jobs_fail_the_build-1.0.dist-info/WHEEL
jenkins_jobs_fail_the_build-1.0.dist-info/RECORD
