Metadata-Version: 2.0
Name: jenkins-jobs-fail-the-build
Version: 1.0
Summary: UNKNOWN
Home-page: https://github.com/doubleo2/jenkins-jobs-fail-the-build
Author: Enrico Mills
Author-email: enrico@nomadlabs.com
License: MIT
Platform: UNKNOWN
Classifier: Development Status :: 5 - Production/Stable
Classifier: Intended Audience :: Developers
Classifier: Topic :: Software Development :: Build Tools
Classifier: License :: OSI Approved :: MIT License
Classifier: Programming Language :: Python :: 2
Classifier: Programming Language :: Python :: 2.7
Requires-Dist: jenkins-job-builder
